README.txt
setup.py
mbe/__init__.py
mbe/access.py
mbe/authentication.py
mbe/cherrypy.py
mbe/constants.py
mbe/groups.py
mbe/logging.py
mbe/node.py
mbe/permission.py
mbe/schema.py
mbe.egg-info/PKG-INFO
mbe.egg-info/SOURCES.txt
mbe.egg-info/dependency_links.txt
mbe.egg-info/top_level.txt
mbe/features/__init__.py
mbe/features/access.feature
mbe/features/authentication.feature
mbe/features/environment.py
mbe/features/node.feature
mbe/features/resources.py
mbe/features/schema.feature
mbe/misc/__init__.py
mbe/misc/aspect_utilities.py
mbe/misc/init.json
mbe/misc/init.py
mbe/misc/schema_mongodb.py
mbe/schemas/__init__.py
mbe/schemas/conditions.json
mbe/schemas/event.json
mbe/schemas/form_json.json
mbe/schemas/group.json
mbe/schemas/node.json
mbe/schemas/right.json
mbe/schemas/session.json
mbe/schemas/type.json
mbe/schemas/user.json