Metadata-Version: 1.0
Name: mbe
Version: 0.7.1.post1
Summary: MBE is a backend written in Python 3 that provides database access, authentication, access control and other features on top of the MongoDB document database.
Home-page: https://github.com/OptimalBPM/mbe
Author: Nicklas Boerjesson
Author-email: nicklas_attheold_optimalbpm.se
License: BSD
Platform: UNKNOWN
